{"trial_id": "011fbc644cc7191f201acd8fb76238d6", "hyperparameters": {"space": [{"class_name": "Int", "config": {"name": "num_layers", "default": null, "min_value": 1, "max_value": 5, "step": 1, "sampling": null}}, {"class_name": "Int", "config": {"name": "units_0", "default": null, "min_value": 6, "max_value": 60, "step": 2, "sampling": null}}, {"class_name": "Choice", "config": {"name": "activ_0", "default": "relu", "values": ["relu", "tanh", "selu", "elu"], "ordered": false}}, {"class_name": "Choice", "config": {"name": "init_0", "default": "truncated_normal", "values": ["truncated_normal", "variance_scaling", "orthogonal", "glorot_normal", "glorot_uniform"], "ordered": false}}, {"class_name": "Choice", "config": {"name": "learning_rate", "default": 0.01, "values": [0.01, 0.0075, 0.005, 0.0025, 0.001, 0.0001], "ordered": true}}, {"class_name": "Int", "config": {"name": "units_1", "default": null, "min_value": 6, "max_value": 60, "step": 2, "sampling": null}}, {"class_name": "Choice", "config": {"name": "activ_1", "default": "relu", "values": ["relu", "tanh", "selu", "elu"], "ordered": false}}, {"class_name": "Choice", "config": {"name": "init_1", "default": "truncated_normal", "values": ["truncated_normal", "variance_scaling", "orthogonal", "glorot_normal", "glorot_uniform"], "ordered": false}}, {"class_name": "Int", "config": {"name": "units_2", "default": null, "min_value": 6, "max_value": 60, "step": 2, "sampling": null}}, {"class_name": "Choice", "config": {"name": "activ_2", "default": "relu", "values": ["relu", "tanh", "selu", "elu"], "ordered": false}}, {"class_name": "Choice", "config": {"name": "init_2", "default": "truncated_normal", "values": ["truncated_normal", "variance_scaling", "orthogonal", "glorot_normal", "glorot_uniform"], "ordered": false}}, {"class_name": "Int", "config": {"name": "units_3", "default": null, "min_value": 6, "max_value": 60, "step": 2, "sampling": null}}, {"class_name": "Choice", "config": {"name": "activ_3", "default": "relu", "values": ["relu", "tanh", "selu", "elu"], "ordered": false}}, {"class_name": "Choice", "config": {"name": "init_3", "default": "truncated_normal", "values": ["truncated_normal", "variance_scaling", "orthogonal", "glorot_normal", "glorot_uniform"], "ordered": false}}, {"class_name": "Int", "config": {"name": "units_4", "default": null, "min_value": 6, "max_value": 60, "step": 2, "sampling": null}}, {"class_name": "Choice", "config": {"name": "activ_4", "default": "relu", "values": ["relu", "tanh", "selu", "elu"], "ordered": false}}, {"class_name": "Choice", "config": {"name": "init_4", "default": "truncated_normal", "values": ["truncated_normal", "variance_scaling", "orthogonal", "glorot_normal", "glorot_uniform"], "ordered": false}}], "values": {"num_layers": 4, "units_0": 18, "activ_0": "relu", "init_0": "truncated_normal", "learning_rate": 0.01, "units_1": 56, "activ_1": "elu", "init_1": "glorot_uniform", "units_2": 8, "activ_2": "elu", "init_2": "glorot_uniform", "units_3": 16, "activ_3": "elu", "init_3": "truncated_normal", "units_4": 60, "activ_4": "relu", "init_4": "truncated_normal", "tuner/epochs": 3, "tuner/initial_epoch": 0, "tuner/bracket": 4, "tuner/round": 0}}, "metrics": {"metrics": {"loss": {"direction": "min", "observations": [{"value": [0.12241446226835251], "step": 0}]}, "mae": {"direction": "min", "observations": [{"value": [0.19418341666460037], "step": 0}]}, "mse": {"direction": "min", "observations": [{"value": [0.12241446226835251], "step": 0}]}, "val_loss": {"direction": "min", "observations": [{"value": [0.1216566413640976], "step": 0}]}, "val_mae": {"direction": "min", "observations": [{"value": [0.18877099454402924], "step": 0}]}, "val_mse": {"direction": "min", "observations": [{"value": [0.1216566413640976], "step": 0}]}}}, "score": 0.12241446226835251, "best_step": 0, "status": "COMPLETED"}